teleop_utils/__init__.py
teleop_utils/iphone/__init__.py
teleop_utils/iphone/iphone_client.py
teleop_utils/iphone/iphone_command.py
teleop_utils/iphone/iphone_controller.py
teleop_utils/iphone/iphone_server.py
teleop_utils/keyboard/__init__.py
teleop_utils/keyboard/keyboard_client.py
teleop_utils/keyboard/keyboard_server.py
teleop_utils/mocap/__init__.py
teleop_utils/mocap/data_descriptions.py
teleop_utils/mocap/mocap_client.py
teleop_utils/mocap/mocap_data.py
teleop_utils/mocap/mocap_server.py
teleop_utils/mocap/natnet_client.py
teleop_utils/mocap/scripts/calculate_time_difference.py
teleop_utils/mocap/scripts/calibrate_mocap_timestamp.py
teleop_utils/mocap/scripts/interpolate_mocap_poses.py
teleop_utils/mocap/scripts/load_mocap_trajectory.py
teleop_utils/mocap/scripts/record_mocap_trajectory.py
teleop_utils/spacemouse/__init__.py
teleop_utils/spacemouse/spacemouse_client.py
teleop_utils/spacemouse/spacemouse_server.py
teleop_utils/utils/__init__.py
teleop_utils/utils/pose_utils.py
teleop_utils-0.1.3.dist-info/licenses/LICENSE
teleop_utils-0.1.3.dist-info/METADATA
teleop_utils-0.1.3.dist-info/WHEEL
teleop_utils-0.1.3.dist-info/entry_points.txt
teleop_utils-0.1.3.dist-info/top_level.txt
teleop_utils-0.1.3.dist-info/RECORD
