Metadata-Version: 2.4
Name: teleop-utils
Version: 0.1.3
Summary: Teleoperation utilities for Robotics
Author-email: Yihuai Gao <yihuai@stanford.edu>
Project-URL: Homepage, https://github.com/yihuai-gao/teleop-utils
Classifier: Programming Language :: Python :: 3
Classifier: License :: OSI Approved :: MIT License
Classifier: Operating System :: OS Independent
License-File: LICENSE
Requires-Dist: numpy
Requires-Dist: transforms3d
Requires-Dist: click
Requires-Dist: robotmq
Requires-Dist: flask
Requires-Dist: flask-socketio
Dynamic: license-file
